{"ID":"25c717d7-bf84-447f-b5c4-838414005e21","childs":{"PS":{"_level":0,"parentID":"25c717d7-bf84-447f-b5c4-838414005e21","firstParentID":"25c717d7-bf84-447f-b5c4-838414005e21","ID":"7d839e66-01d9-4810-9b01-bb46b11a539a","childs":{"сальдо":{"_level":1,"parentID":"7d839e66-01d9-4810-9b01-bb46b11a539a","firstParentID":"25c717d7-bf84-447f-b5c4-838414005e21","ID":"58c44478-a9c4-4e36-89d5-05be1719c081","childs":{"формула":{"_level":2,"parentID":"58c44478-a9c4-4e36-89d5-05be1719c081","firstParentID":"25c717d7-bf84-447f-b5c4-838414005e21","ID":"935c95c2-b55a-439f-b19d-4c92474c281e","childs":null,"emcosID":null,"emcosMLID":null,"codMaketTEP":null,"codTEP":null,"WSName":"PS","rangeAddress":"$R$13:$R$49","headAddress":"$R$13","bodyAddress":"$R$14:$R$49","_name":"формула"}},"emcosID":null,"emcosMLID":null,"codMaketTEP":null,"codTEP":null,"WSName":"PS","rangeAddress":"$R$12:$R$49","headAddress":"$R$12","bodyAddress":"$R$13:$R$49","_name":"сальдо"}},"emcosID":null,"emcosMLID":null,"codMaketTEP":null,"codTEP":null,"WSName":"PS","rangeAddress":"$R$11:$R$49","headAddress":"$R$11","bodyAddress":"$R$12:$R$49","_name":"Сальдо АЖК без КГЭС Общее"},"DB":{"_level":0,"parentID":"25c717d7-bf84-447f-b5c4-838414005e21","firstParentID":"25c717d7-bf84-447f-b5c4-838414005e21","ID":"9278f42b-2c68-4fc4-9463-7e26669d4cff","childs":{"сальдо":{"_level":1,"parentID":"9278f42b-2c68-4fc4-9463-7e26669d4cff","firstParentID":"25c717d7-bf84-447f-b5c4-838414005e21","ID":"d9b65a66-b185-4e56-be66-3b9af00319c5","childs":{"код":{"_level":2,"parentID":"d9b65a66-b185-4e56-be66-3b9af00319c5","firstParentID":"25c717d7-bf84-447f-b5c4-838414005e21","ID":"8468c8d8-ecfc-4343-b08d-247cbb6c2e30","childs":null,"emcosID":null,"emcosMLID":null,"codMaketTEP":null,"codTEP":null,"WSName":"DB","rangeAddress":"$GT$353:$GT$390","headAddress":"$GT$353","bodyAddress":"$GT$354:$GT$390","_name":"код"},"основное":{"_level":2,"parentID":"d9b65a66-b185-4e56-be66-3b9af00319c5","firstParentID":"25c717d7-bf84-447f-b5c4-838414005e21","ID":"474956fe-42c1-4d03-bafe-6a8f30f5897a","childs":null,"emcosID":null,"emcosMLID":null,"codMaketTEP":null,"codTEP":null,"WSName":"DB","rangeAddress":"$GU$353:$GU$390","headAddress":"$GU$353","bodyAddress":"$GU$354:$GU$390","_name":"основное"},"корректировка факт":{"_level":2,"parentID":"d9b65a66-b185-4e56-be66-3b9af00319c5","firstParentID":"25c717d7-bf84-447f-b5c4-838414005e21","ID":"e5133834-8564-4d48-ae10-dab6c945608e","childs":null,"emcosID":null,"emcosMLID":null,"codMaketTEP":null,"codTEP":null,"WSName":"DB","rangeAddress":"$GV$353:$GV$390","headAddress":"$GV$353","bodyAddress":"$GV$354:$GV$390","_name":"корректировка факт"},"ручное":{"_level":2,"parentID":"d9b65a66-b185-4e56-be66-3b9af00319c5","firstParentID":"25c717d7-bf84-447f-b5c4-838414005e21","ID":"5c1a3eb7-c95e-4ef4-8f7e-ca4600394f98","childs":null,"emcosID":null,"emcosMLID":null,"codMaketTEP":null,"codTEP":null,"WSName":"DB","rangeAddress":"$GW$353:$GW$390","headAddress":"$GW$353","bodyAddress":"$GW$354:$GW$390","_name":"ручное"},"формула":{"_level":2,"parentID":"d9b65a66-b185-4e56-be66-3b9af00319c5","firstParentID":"25c717d7-bf84-447f-b5c4-838414005e21","ID":"f1a55982-997b-4aa5-ad8f-a316423e8383","childs":null,"emcosID":null,"emcosMLID":null,"codMaketTEP":null,"codTEP":null,"WSName":"DB","rangeAddress":"$GX$353:$GX$390","headAddress":"$GX$353","bodyAddress":"$GX$354:$GX$390","_name":"формула"},"оперативное":{"_level":2,"parentID":"d9b65a66-b185-4e56-be66-3b9af00319c5","firstParentID":"25c717d7-bf84-447f-b5c4-838414005e21","ID":"af90a584-4f99-423d-b8a8-b31c710d6790","childs":null,"emcosID":null,"emcosMLID":null,"codMaketTEP":null,"codTEP":null,"WSName":"DB","rangeAddress":"$GY$353:$GY$390","headAddress":"$GY$353","bodyAddress":"$GY$354:$GY$390","_name":"оперативное"}},"emcosID":null,"emcosMLID":null,"codMaketTEP":null,"codTEP":null,"WSName":"DB","rangeAddress":"$GT$352:$GY$390","headAddress":"$GT$352:$GY$352","bodyAddress":"$GT$353:$GY$390","_name":"сальдо"}},"emcosID":null,"emcosMLID":null,"codMaketTEP":null,"codTEP":null,"WSName":"DB","rangeAddress":"$GT$351:$GY$390","headAddress":"$GT$351:$GY$351","bodyAddress":"$GT$352:$GY$390","_name":"Сальдо АЖК без КГЭС Общее"}},"codPlan":null,"meterCoef":null,"_name":"Сальдо АЖК без КГЭС Общее"}