{"ID":"d0db3458-053f-436e-8d02-926beb386cae","childs":{"PS":{"_level":0,"parentID":"d0db3458-053f-436e-8d02-926beb386cae","firstParentID":"d0db3458-053f-436e-8d02-926beb386cae","ID":"dae0af3e-b310-477d-a89a-18a10a003e7d","childs":{"прием":{"_level":1,"parentID":"dae0af3e-b310-477d-a89a-18a10a003e7d","firstParentID":"d0db3458-053f-436e-8d02-926beb386cae","ID":"0ddc6c68-f505-44cc-92f5-53d8ef1321eb","childs":{"ручное":{"_level":2,"parentID":"0ddc6c68-f505-44cc-92f5-53d8ef1321eb","firstParentID":"d0db3458-053f-436e-8d02-926beb386cae","ID":"bc5035e7-5479-4834-a232-9b1d653c4e34","childs":null,"emcosID":null,"emcosMLID":null,"codMaketTEP":null,"codTEP":null,"WSName":"PS","rangeAddress":"$AN$185:$AN$221","headAddress":"$AN$185","bodyAddress":"$AN$186:$AN$221","_name":"ручное"}},"emcosID":null,"emcosMLID":null,"codMaketTEP":null,"codTEP":null,"WSName":"PS","rangeAddress":"$AN$184:$AN$221","headAddress":"$AN$184","bodyAddress":"$AN$185:$AN$221","_name":"прием"}},"emcosID":null,"emcosMLID":null,"codMaketTEP":null,"codTEP":null,"WSName":"PS","rangeAddress":"$AN$183:$AN$221","headAddress":"$AN$183","bodyAddress":"$AN$184:$AN$221","_name":"с.н. Mistral Energy СЭС Каскелен 50"},"DB":{"_level":0,"parentID":"d0db3458-053f-436e-8d02-926beb386cae","firstParentID":"d0db3458-053f-436e-8d02-926beb386cae","ID":"f2094695-2858-45bb-b038-b3063451c5af","childs":{"прием":{"_level":1,"parentID":"f2094695-2858-45bb-b038-b3063451c5af","firstParentID":"d0db3458-053f-436e-8d02-926beb386cae","ID":"b1030035-5825-4291-bd8c-c56a807fcc1c","childs":{"код":{"_level":2,"parentID":"b1030035-5825-4291-bd8c-c56a807fcc1c","firstParentID":"d0db3458-053f-436e-8d02-926beb386cae","ID":"7be407ad-0dc2-4604-8721-841b7b1c29f6","childs":null,"emcosID":null,"emcosMLID":null,"codMaketTEP":null,"codTEP":null,"WSName":"DB","rangeAddress":"$BU$396:$BU$433","headAddress":"$BU$396","bodyAddress":"$BU$397:$BU$433","_name":"код"},"основное":{"_level":2,"parentID":"b1030035-5825-4291-bd8c-c56a807fcc1c","firstParentID":"d0db3458-053f-436e-8d02-926beb386cae","ID":"2b910c5e-1948-4d9e-854f-f85015be250a","childs":null,"emcosID":null,"emcosMLID":null,"codMaketTEP":null,"codTEP":null,"WSName":"DB","rangeAddress":"$BV$396:$BV$433","headAddress":"$BV$396","bodyAddress":"$BV$397:$BV$433","_name":"основное"},"корректировка факт":{"_level":2,"parentID":"b1030035-5825-4291-bd8c-c56a807fcc1c","firstParentID":"d0db3458-053f-436e-8d02-926beb386cae","ID":"0a2b22c9-3be1-4398-afd4-11aefb84e907","childs":null,"emcosID":null,"emcosMLID":null,"codMaketTEP":null,"codTEP":null,"WSName":"DB","rangeAddress":"$BW$396:$BW$433","headAddress":"$BW$396","bodyAddress":"$BW$397:$BW$433","_name":"корректировка факт"},"ручное":{"_level":2,"parentID":"b1030035-5825-4291-bd8c-c56a807fcc1c","firstParentID":"d0db3458-053f-436e-8d02-926beb386cae","ID":"ab086057-05f6-42e9-a066-fabb19574d35","childs":null,"emcosID":null,"emcosMLID":null,"codMaketTEP":null,"codTEP":null,"WSName":"DB","rangeAddress":"$BX$396:$BX$433","headAddress":"$BX$396","bodyAddress":"$BX$397:$BX$433","_name":"ручное"}},"emcosID":null,"emcosMLID":null,"codMaketTEP":null,"codTEP":null,"WSName":"DB","rangeAddress":"$BU$395:$BX$433","headAddress":"$BU$395:$BX$395","bodyAddress":"$BU$396:$BX$433","_name":"прием"}},"emcosID":null,"emcosMLID":null,"codMaketTEP":null,"codTEP":null,"WSName":"DB","rangeAddress":"$BU$394:$BX$433","headAddress":"$BU$394:$BX$394","bodyAddress":"$BU$395:$BX$433","_name":"с.н. Mistral Energy СЭС Каскелен 50"}},"codPlan":null,"meterCoef":null,"_name":"с.н. Mistral Energy СЭС Каскелен 50"}